computational_methods/__init__.py
computational_methods/computational_methods.py
math_programming/__init__.py
math_programming/math_programming.py
systems_modeling/__init__.py
systems_modeling/systems_modeling.py
insy-0.1.0.dist-info/METADATA
insy-0.1.0.dist-info/WHEEL
insy-0.1.0.dist-info/top_level.txt
insy-0.1.0.dist-info/RECORD
