Metadata-Version: 2.4
Name: insy
Version: 0.1.0
Summary: A library for computational methods, mathematical programming, and system modeling
Author: Gevorg Melqonyan
Author-email: Gevorg Melqonyan <gevorgmelqonyan03@gmail.com>
License: MIT
Classifier: Programming Language :: Python :: 3
Classifier: License :: OSI Approved :: MIT License
Classifier: Operating System :: OS Independent
Requires-Python: >=3.7
Dynamic: author
Dynamic: requires-python
